{
  "active": true,
  "connections": {
    "Webhook": {
      "main": [
        [
          {
            "node": "Respond to Webhook",
            "type": "main",
            "index": 0
          },
          {
            "node": "Wait",
            "type": "main",
            "index": 0
          }
        ]
      ]
    },
    "When clicking ‘Execute workflow’": {
      "main": [
        [
          {
            "node": "Get many workflows",
            "type": "main",
            "index": 0
          }
        ]
      ]
    },
    "Get many workflows": {
      "main": [
        [
          {
            "node": "Filter",
            "type": "main",
            "index": 0
          }
        ]
      ]
    },
    "Loop Over Items": {
      "main": [
        [],
        []
      ]
    },
    "Replace Me": {
      "main": [
        []
      ]
    }
  },
  "createdAt": "2025-08-28T11:13:46.807Z",
  "id": "adRc6pBw3yfVYOxh",
  "isArchived": false,
  "meta": {
    "templateCredsSetupCompleted": true
  },
  "name": "TEST > Webhook GET",
  "nodes": [
    {
      "parameters": {
        "path": "/test-bassel",
        "responseMode": "responseNode",
        "options": {
          "rawBody": false
        }
      },
      "type": "n8n-nodes-base.webhook",
      "typeVersion": 2.1,
      "position": [
        -432,
        -48
      ],
      "id": "6cbe8631-8561-4b5e-b248-f24cca04f029",
      "name": "Webhook",
      "webhookId": "1e9fab17-408f-4c13-86e5-183b96a361d6"
    },
    {
      "parameters": {
        "respondWith": "text",
        "responseBody": "<!DOCTYPE html>|<html lang=\"fr\"><head>  <meta charset=\"UTF-8\" />  <meta name=\"viewport\" content=\"width=device-width, initial-scale=1\" />  <title>Merci</title>  <style>    body {font-family: system-ui, -apple-system, Segoe UI, Roboto, Arial, sans-serif; background:#f8fafc; margin:0;}    .wrap {max-width:640px; margin:12vh auto; background:#fff; border-radius:16px; padding:40px; box-shadow:0 10px 30px rgba(0,0,0,0.06);}    h1 {margin:0 0 10px; font-size:28px}    p {margin:0 0 14px; color:#334155}    .small {font-size:12px; color:#64748b}    .btn {display:inline-block; margin-top:18px; padding:10px 16px; border-radius:10px; border:1px solid #e2e8f0; text-decoration:none; color:#0f172a}  </style></head><body>  <main class=\"wrap\">    <h1>Merci pour votre soumission 🎉</h1>    <p>Nous avons bien reçu vos informations.</p>    <p class=\"small\">Si vous êtes arrivé ici après un formulaire, vous pouvez fermer cet onglet.</p>    <a class=\"btn\" href=\"/\">Retour</a>  </main></body></html>",
        "options": {
          "responseCode": 200,
          "responseHeaders": {
            "entries": [
              {
                "name": "Content-Type",
                "value": "text/html; charset=utf-8"
              }
            ]
          }
        }
      },
      "id": "bbfc46cb-8c1b-4b49-9934-86f082c29fe9",
      "name": "Respond to Webhook",
      "type": "n8n-nodes-base.respondToWebhook",
      "typeVersion": 1,
      "position": [
        -128,
        -208
      ]
    },
    {
      "parameters": {},
      "type": "n8n-nodes-base.wait",
      "typeVersion": 1.1,
      "position": [
        -144,
        48
      ],
      "id": "c0768d7a-8a36-48a8-9973-48a91ab1471c",
      "name": "Wait",
      "webhookId": "ce765b26-a57d-457a-98c0-4f1c862aa1a4"
    },
    {
      "parameters": {},
      "type": "n8n-nodes-base.manualTrigger",
      "typeVersion": 1,
      "position": [
        -544,
        -464
      ],
      "id": "2dc837a8-9377-4a07-a129-54430357da98",
      "name": "When clicking ‘Execute workflow’"
    },
    {
      "parameters": {
        "filters": {},
        "requestOptions": {}
      },
      "type": "n8n-nodes-base.n8n",
      "typeVersion": 1,
      "position": [
        -336,
        -464
      ],
      "id": "97428ba9-1817-4ab6-880b-425bd13a1ad0",
      "name": "Get many workflows",
      "credentials": {
        "n8nApi": {
          "id": "DeDKPUGV1gyQwspX",
          "name": "n8n local"
        }
      }
    },
    {
      "parameters": {
        "operation": "create",
        "workflowObject": "={{ $json.toJsonString() }}",
        "requestOptions": {}
      },
      "type": "n8n-nodes-base.n8n",
      "typeVersion": 1,
      "position": [
        592,
        -400
      ],
      "id": "f821fdf2-8db2-4e26-bbed-082b4341e2ff",
      "name": "Create a workflow",
      "credentials": {
        "n8nApi": {
          "id": "DeDKPUGV1gyQwspX",
          "name": "n8n local"
        }
      }
    },
    {
      "parameters": {
        "options": {}
      },
      "type": "n8n-nodes-base.set",
      "typeVersion": 3.4,
      "position": [
        544,
        -48
      ],
      "id": "495b0c79-fcda-4e50-a568-84a72da1b8e4",
      "name": "Edit Fields"
    },
    {
      "parameters": {
        "options": {}
      },
      "type": "n8n-nodes-base.splitInBatches",
      "typeVersion": 3,
      "position": [
        240,
        -448
      ],
      "id": "c9c4cd3c-1951-4cbd-9b56-07be38d06173",
      "name": "Loop Over Items"
    },
    {
      "parameters": {},
      "type": "n8n-nodes-base.noOp",
      "name": "Replace Me",
      "typeVersion": 1,
      "position": [
        272,
        -48
      ],
      "id": "f1465e6d-2271-4218-ab11-fb165cdb6012"
    },
    {
      "parameters": {
        "conditions": {
          "options": {
            "caseSensitive": true,
            "leftValue": "",
            "typeValidation": "strict",
            "version": 2
          },
          "conditions": [
            {
              "id": "25032b1c-c4fa-481b-93dd-2b618d1a150e",
              "leftValue": "={{ $json.isArchived }}",
              "rightValue": "",
              "operator": {
                "type": "boolean",
                "operation": "false",
                "singleValue": true
              }
            }
          ],
          "combinator": "and"
        },
        "options": {}
      },
      "type": "n8n-nodes-base.filter",
      "typeVersion": 2.2,
      "position": [
        -128,
        -464
      ],
      "id": "69b54503-2ec0-42a0-9cec-df79e72dae8c",
      "name": "Filter"
    }
  ],
  "repo_name": "boost-prospect-v2",
  "repo_owner": "ultimvision",
  "repo_path": "workflows",
  "settings": {
    "executionOrder": "v1"
  },
  "shared": [
    {
      "createdAt": "2025-08-28T11:13:46.807Z",
      "updatedAt": "2025-08-28T11:13:46.807Z",
      "role": "workflow:owner",
      "workflowId": "adRc6pBw3yfVYOxh",
      "projectId": "zxVtQj8AiJx7hlkL"
    }
  ],
  "staticData": null,
  "tags": [
    {
      "createdAt": "2025-09-01T12:44:01.185Z",
      "updatedAt": "2025-09-01T12:44:01.185Z",
      "id": "youa0jSYMmDkNoor",
      "name": "Test"
    }
  ],
  "triggerCount": 1,
  "updatedAt": "2025-09-01T14:50:48.041Z",
  "versionId": "202fceee-4fa1-4fd1-ab8f-bfeff817622f"
}